kreta/__init__.py
kreta/models.py
kreta/dkt/__init__.py
kreta/dkt/endpoints.py
kreta/dkt/models.py
kreta/eadmin/__init__.py
kreta/eadmin/endpoints.py
kreta/eadmin/models.py
kreta/global_api/__init__.py
kreta/global_api/endpoints.py
kreta/global_api/models.py
kreta/idp/__init__.py
kreta/idp/auth_session.py
kreta/idp/auth_token.py
kreta/idp/login.py
kreta/mobile/__init__.py
kreta/mobile/endpoints.py
kreta/mobile/models.py
kreta/utils/api_models_source
kreta/utils/dkt_models_source
kreta/utils/eadmin_models_source
kreta/utils/global_models_source
kreta/utils/mobile_models_source
kreta/utils/model_make.py
kreta/utils/utils.py
e_kreta_hun0r-2.0.12.dist-info/METADATA
e_kreta_hun0r-2.0.12.dist-info/WHEEL
e_kreta_hun0r-2.0.12.dist-info/licenses/LICENSE
e_kreta_hun0r-2.0.12.dist-info/RECORD
