Metadata-Version: 2.4
Name: e-kreta-hun0r
Version: 2.0.12
Summary: E-Kréta API wrapper
Project-URL: Homepage, https://github.com/hun0r/e-kreta-hun0r-2.0
Project-URL: Issues, https://github.com/hun0r/e-kreta-hun0r-2.0/issues
Author-email: hun0r <kiskukac1024@gmail.com>
License-Expression: MIT
License-File: LICENSE
Keywords: API,e-kreta,wrapper
Classifier: Development Status :: 4 - Beta
Classifier: Intended Audience :: Developers
Classifier: Operating System :: OS Independent
Classifier: Programming Language :: Python :: 3
Requires-Python: >=3.9
Requires-Dist: beautifulsoup4
Requires-Dist: pydantic
Requires-Dist: pyjwt
Requires-Dist: requests
